Workbook

Sheet Summary
A1: Sales & Operations Report - Sample Grocery Store
A2: All figures are formulas linked to the Data_* and Inventory sheets.
A3: Period start | B3: =MIN(Data_Sales!$A$2:$A$1473) -> 46204
A4: Period end | B4: =MAX(Data_Sales!$A$2:$A$1473) -> 46295
A5: Days in period | B5: =B4-B3+1 -> 92
A7: Total Revenue | B7: =SUM(Data_Sales!$H$2:$H$1473) -> 33711
A8: Cost of Goods Sold | B8: =SUM(Data_Sales!$J$2:$J$1473) -> 20802.75
A9: Gross Profit | B9: =B7-B8 -> 12908.25
A10: Gross Margin % | B10: =IF(B7=0,0,B9/B7) -> 0.38290914
A11: Operating Expenses | B11: =SUM(Data_Expenses!$E$2:$E$40) -> 8907.51
A12: Net Profit | B12: =B9-B11 -> 4000.74
A13: Net Margin % | B13: =IF(B7=0,0,B12/B7) -> 0.11867758
A14: Products to Reorder | B14: =COUNTIF(Inventory!$H$2:$H$17,"REORDER") -> 4
A17: Monthly performance
A18: Month | B18: Revenue | C18: COGS | D18: Gross Profit | E18: Operating Expenses | F18: Net Profit | G18: Net Margin %
A19: 46204 | B19: =SUMIFS(Data_Sales!$H$2:$H$1473,Data_Sales!$B$2:$B$1473,$A19) -> 11001.55 | C19: =SUMIFS(Data_Sales!$J$2:$J$1473,Data_Sales!$B$2:$B$1473,$A19) -> 6782.65 | D19: =B19-C19 -> 4218.9 | E19: =SUMIFS(Data_Expenses!$E$2:$E$40,Data_Expenses!$B$2:$B$40,$A19) -> 2856.94 | F19: =D19-E19 -> 1361.96 | G19: =IF(B19=0,0,F19/B19) -> 0.1237971
A20: 46235 | B20: =SUMIFS(Data_Sales!$H$2:$H$1473,Data_Sales!$B$2:$B$1473,$A20) -> 11340 | C20: =SUMIFS(Data_Sales!$J$2:$J$1473,Data_Sales!$B$2:$B$1473,$A20) -> 6996.65 | D20: =B20-C20 -> 4343.35 | E20: =SUMIFS(Data_Expenses!$E$2:$E$40,Data_Expenses!$B$2:$B$40,$A20) -> 3100.85 | F20: =D20-E20 -> 1242.5 | G20: =IF(B20=0,0,F20/B20) -> 0.1095679
A21: 46266 | B21: =SUMIFS(Data_Sales!$H$2:$H$1473,Data_Sales!$B$2:$B$1473,$A21) -> 11369.45 | C21: =SUMIFS(Data_Sales!$J$2:$J$1473,Data_Sales!$B$2:$B$1473,$A21) -> 7023.45 | D21: =B21-C21 -> 4346 | E21: =SUMIFS(Data_Expenses!$E$2:$E$40,Data_Expenses!$B$2:$B$40,$A21) -> 2949.72 | F21: =D21-E21 -> 1396.28 | G21: =IF(B21=0,0,F21/B21) -> 0.12280981
A22: Total | B22: =SUM(B19:B21) -> 33711 | C22: =SUM(C19:C21) -> 20802.75 | D22: =SUM(D19:D21) -> 12908.25 | E22: =SUM(E19:E21) -> 8907.51 | F22: =SUM(F19:F21) -> 4000.74 | G22: =IF(B22=0,0,F22/B22) -> 0.11867758
A24: Notes
A25: - Gross Profit = Revenue - COGS. COGS uses the unit cost from the Inventory sheet.
A26: - Net Profit = Gross Profit - Operating Expenses (rent, payroll, utilities, etc.).
A27: - The sample data included in this repository is synthetic.

Sheet Sales_by_Category
A1: Sales by Category
A3: Revenue by category and month
A4: Category | B4: 46204 | C4: 46235 | D4: 46266 | E4: Total | F4: % of Revenue
A5: Dairy | B5: =SUMIFS(Data_Sales!$H$2:$H$1473,Data_Sales!$E$2:$E$1473,$A5,Data_Sales!$B$2:$B$1473,B$4) -> 2988.8 | C5: =SUMIFS(Data_Sales!$H$2:$H$1473,Data_Sales!$E$2:$E$1473,$A5,Data_Sales!$B$2:$B$1473,C$4) -> 3144.3 | D5: =SUMIFS(Data_Sales!$H$2:$H$1473,Data_Sales!$E$2:$E$1473,$A5,Data_Sales!$B$2:$B$1473,D$4) -> 3203.6 | E5: =SUM(B5:D5) -> 9336.7 | F5: =IF(E$9=0,0,E5/E$9) -> 0.27696301
A6: Beverages | B6: =SUMIFS(Data_Sales!$H$2:$H$1473,Data_Sales!$E$2:$E$1473,$A6,Data_Sales!$B$2:$B$1473,B$4) -> 2758.85 | C6: =SUMIFS(Data_Sales!$H$2:$H$1473,Data_Sales!$E$2:$E$1473,$A6,Data_Sales!$B$2:$B$1473,C$4) -> 2888 | D6: =SUMIFS(Data_Sales!$H$2:$H$1473,Data_Sales!$E$2:$E$1473,$A6,Data_Sales!$B$2:$B$1473,D$4) -> 2786.65 | E6: =SUM(B6:D6) -> 8433.5 | F6: =IF(E$9=0,0,E6/E$9) -> 0.25017057
A7: Snacks | B7: =SUMIFS(Data_Sales!$H$2:$H$1473,Data_Sales!$E$2:$E$1473,$A7,Data_Sales!$B$2:$B$1473,B$4) -> 2762.7 | C7: =SUMIFS(Data_Sales!$H$2:$H$1473,Data_Sales!$E$2:$E$1473,$A7,Data_Sales!$B$2:$B$1473,C$4) -> 2744.6 | D7: =SUMIFS(Data_Sales!$H$2:$H$1473,Data_Sales!$E$2:$E$1473,$A7,Data_Sales!$B$2:$B$1473,D$4) -> 2716.4 | E7: =SUM(B7:D7) -> 8223.7 | F7: =IF(E$9=0,0,E7/E$9) -> 0.24394708
A8: Cleaning | B8: =SUMIFS(Data_Sales!$H$2:$H$1473,Data_Sales!$E$2:$E$1473,$A8,Data_Sales!$B$2:$B$1473,B$4) -> 2491.2 | C8: =SUMIFS(Data_Sales!$H$2:$H$1473,Data_Sales!$E$2:$E$1473,$A8,Data_Sales!$B$2:$B$1473,C$4) -> 2563.1 | D8: =SUMIFS(Data_Sales!$H$2:$H$1473,Data_Sales!$E$2:$E$1473,$A8,Data_Sales!$B$2:$B$1473,D$4) -> 2662.8 | E8: =SUM(B8:D8) -> 7717.1 | F8: =IF(E$9=0,0,E8/E$9) -> 0.22891934
A9: Total | B9: =SUM(B5:B8) -> 11001.55 | C9: =SUM(C5:C8) -> 11340 | D9: =SUM(D5:D8) -> 11369.45 | E9: =SUM(E5:E8) -> 33711 | F9: =SUM(F5:F8) -> 1
A11: Profitability by category
A12: Category | B12: Revenue | C12: Gross Profit | D12: Gross Margin %
A13: Dairy | B13: =SUMIFS(Data_Sales!$H$2:$H$1473,Data_Sales!$E$2:$E$1473,$A13) -> 9336.7 | C13: =SUMIFS(Data_Sales!$K$2:$K$1473,Data_Sales!$E$2:$E$1473,$A13) -> 2983.35 | D13: =IF(B13=0,0,C13/B13) -> 0.31952938
A14: Beverages | B14: =SUMIFS(Data_Sales!$H$2:$H$1473,Data_Sales!$E$2:$E$1473,$A14) -> 8433.5 | C14: =SUMIFS(Data_Sales!$K$2:$K$1473,Data_Sales!$E$2:$E$1473,$A14) -> 3598.2 | D14: =IF(B14=0,0,C14/B14) -> 0.4266556
A15: Snacks | B15: =SUMIFS(Data_Sales!$H$2:$H$1473,Data_Sales!$E$2:$E$1473,$A15) -> 8223.7 | C15: =SUMIFS(Data_Sales!$K$2:$K$1473,Data_Sales!$E$2:$E$1473,$A15) -> 3478.8 | D15: =IF(B15=0,0,C15/B15) -> 0.42302127
A16: Cleaning | B16: =SUMIFS(Data_Sales!$H$2:$H$1473,Data_Sales!$E$2:$E$1473,$A16) -> 7717.1 | C16: =SUMIFS(Data_Sales!$K$2:$K$1473,Data_Sales!$E$2:$E$1473,$A16) -> 2847.9 | D16: =IF(B16=0,0,C16/B16) -> 0.36903759

Sheet Product_Ranking
A1: Product Ranking
A2: Products are listed by revenue at the time the report was generated.
A4: Rank | B4: Product ID | C4: Product | D4: Category | E4: Units Sold | F4: Revenue | G4: Gross Profit | H4: Gross Margin % | I4: % of Revenue
A5: =RANK(F5,$F$5:$F$20) -> 1 | B5: P09 | C5: Whole Milk 1L | D5: Dairy | E5: =SUMIFS(Data_Sales!$F$2:$F$1473,Data_Sales!$C$2:$C$1473,$B5) -> 2561 | F5: =SUMIFS(Data_Sales!$H$2:$H$1473,Data_Sales!$C$2:$C$1473,$B5) -> 3073.2 | G5: =SUMIFS(Data_Sales!$K$2:$K$1473,Data_Sales!$C$2:$C$1473,$B5) -> 896.35 | H5: =IF(F5=0,0,G5/F5) -> 0.29166667 | I5: =IF(F$21=0,0,F5/F$21) -> 0.091163122
A6: =RANK(F6,$F$5:$F$20) -> 2 | B6: P01 | C6: Cola 600ml | D6: Beverages | E6: =SUMIFS(Data_Sales!$F$2:$F$1473,Data_Sales!$C$2:$C$1473,$B6) -> 2839 | F6: =SUMIFS(Data_Sales!$H$2:$H$1473,Data_Sales!$C$2:$C$1473,$B6) -> 2839 | G6: =SUMIFS(Data_Sales!$K$2:$K$1473,Data_Sales!$C$2:$C$1473,$B6) -> 1135.6 | H6: =IF(F6=0,0,G6/F6) -> 0.4 | I6: =IF(F$21=0,0,F6/F$21) -> 0.084215835
A7: =RANK(F7,$F$5:$F$20) -> 3 | B7: P05 | C7: Potato Chips | D7: Snacks | E7: =SUMIFS(Data_Sales!$F$2:$F$1473,Data_Sales!$C$2:$C$1473,$B7) -> 2161 | F7: =SUMIFS(Data_Sales!$H$2:$H$1473,Data_Sales!$C$2:$C$1473,$B7) -> 2809.3 | G7: =SUMIFS(Data_Sales!$K$2:$K$1473,Data_Sales!$C$2:$C$1473,$B7) -> 1080.5 | H7: =IF(F7=0,0,G7/F7) -> 0.38461538 | I7: =IF(F$21=0,0,F7/F$21) -> 0.083334817
A8: =RANK(F8,$F$5:$F$20) -> 4 | B8: P11 | C8: Cheese 400g | D8: Dairy | E8: =SUMIFS(Data_Sales!$F$2:$F$1473,Data_Sales!$C$2:$C$1473,$B8) -> 738 | F8: =SUMIFS(Data_Sales!$H$2:$H$1473,Data_Sales!$C$2:$C$1473,$B8) -> 2804.4 | G8: =SUMIFS(Data_Sales!$K$2:$K$1473,Data_Sales!$C$2:$C$1473,$B8) -> 885.6 | H8: =IF(F8=0,0,G8/F8) -> 0.31578947 | I8: =IF(F$21=0,0,F8/F$21) -> 0.083189463
A9: =RANK(F9,$F$5:$F$20) -> 5 | B9: P14 | C9: Laundry Detergent | D9: Cleaning | E9: =SUMIFS(Data_Sales!$F$2:$F$1473,Data_Sales!$C$2:$C$1473,$B9) -> 531 | F9: =SUMIFS(Data_Sales!$H$2:$H$1473,Data_Sales!$C$2:$C$1473,$B9) -> 2761.2 | G9: =SUMIFS(Data_Sales!$K$2:$K$1473,Data_Sales!$C$2:$C$1473,$B9) -> 902.7 | H9: =IF(F9=0,0,G9/F9) -> 0.32692308 | I9: =IF(F$21=0,0,F9/F$21) -> 0.081907983
A10: =RANK(F10,$F$5:$F$20) -> 6 | B10: P10 | C10: Yogurt 1kg | D10: Dairy | E10: =SUMIFS(Data_Sales!$F$2:$F$1473,Data_Sales!$C$2:$C$1473,$B10) -> 1036 | F10: =SUMIFS(Data_Sales!$H$2:$H$1473,Data_Sales!$C$2:$C$1473,$B10) -> 2279.2 | G10: =SUMIFS(Data_Sales!$K$2:$K$1473,Data_Sales!$C$2:$C$1473,$B10) -> 828.8 | H10: =IF(F10=0,0,G10/F10) -> 0.36363636 | I10: =IF(F$21=0,0,F10/F$21) -> 0.067609979
A11: =RANK(F11,$F$5:$F$20) -> 7 | B11: P07 | C11: Cookies | D11: Snacks | E11: =SUMIFS(Data_Sales!$F$2:$F$1473,Data_Sales!$C$2:$C$1473,$B11) -> 1795 | F11: =SUMIFS(Data_Sales!$H$2:$H$1473,Data_Sales!$C$2:$C$1473,$B11) -> 2154 | G11: =SUMIFS(Data_Sales!$K$2:$K$1473,Data_Sales!$C$2:$C$1473,$B11) -> 897.5 | H11: =IF(F11=0,0,G11/F11) -> 0.41666667 | I11: =IF(F$21=0,0,F11/F$21) -> 0.063896058
A12: =RANK(F12,$F$5:$F$20) -> 8 | B12: P08 | C12: Chocolate Bar | D12: Snacks | E12: =SUMIFS(Data_Sales!$F$2:$F$1473,Data_Sales!$C$2:$C$1473,$B12) -> 2328 | F12: =SUMIFS(Data_Sales!$H$2:$H$1473,Data_Sales!$C$2:$C$1473,$B12) -> 1978.8 | G12: =SUMIFS(Data_Sales!$K$2:$K$1473,Data_Sales!$C$2:$C$1473,$B12) -> 931.2 | H12: =IF(F12=0,0,G12/F12) -> 0.47058824 | I12: =IF(F$21=0,0,F12/F$21) -> 0.058698941
A13: =RANK(F13,$F$5:$F$20) -> 9 | B13: P02 | C13: Orange Soda 600ml | D13: Beverages | E13: =SUMIFS(Data_Sales!$F$2:$F$1473,Data_Sales!$C$2:$C$1473,$B13) -> 1988 | F13: =SUMIFS(Data_Sales!$H$2:$H$1473,Data_Sales!$C$2:$C$1473,$B13) -> 1888.6 | G13: =SUMIFS(Data_Sales!$K$2:$K$1473,Data_Sales!$C$2:$C$1473,$B13) -> 795.2 | H13: =IF(F13=0,0,G13/F13) -> 0.42105263 | I13: =IF(F$21=0,0,F13/F$21) -> 0.056023257
A14: =RANK(F14,$F$5:$F$20) -> 10 | B14: P16 | C14: Paper Towels | D14: Cleaning | E14: =SUMIFS(Data_Sales!$F$2:$F$1473,Data_Sales!$C$2:$C$1473,$B14) -> 752 | F14: =SUMIFS(Data_Sales!$H$2:$H$1473,Data_Sales!$C$2:$C$1473,$B14) -> 1880 | G14: =SUMIFS(Data_Sales!$K$2:$K$1473,Data_Sales!$C$2:$C$1473,$B14) -> 676.8 | H14: =IF(F14=0,0,G14/F14) -> 0.36 | I14: =IF(F$21=0,0,F14/F$21) -> 0.055768147
A15: =RANK(F15,$F$5:$F$20) -> 11 | B15: P04 | C15: Fruit Juice 1L | D15: Beverages | E15: =SUMIFS(Data_Sales!$F$2:$F$1473,Data_Sales!$C$2:$C$1473,$B15) -> 1237 | F15: =SUMIFS(Data_Sales!$H$2:$H$1473,Data_Sales!$C$2:$C$1473,$B15) -> 1855.5 | G15: =SUMIFS(Data_Sales!$K$2:$K$1473,Data_Sales!$C$2:$C$1473,$B15) -> 742.2 | H15: =IF(F15=0,0,G15/F15) -> 0.4 | I15: =IF(F$21=0,0,F15/F$21) -> 0.055041381
A16: =RANK(F16,$F$5:$F$20) -> 12 | B16: P03 | C16: Bottled Water 1L | D16: Beverages | E16: =SUMIFS(Data_Sales!$F$2:$F$1473,Data_Sales!$C$2:$C$1473,$B16) -> 3084 | F16: =SUMIFS(Data_Sales!$H$2:$H$1473,Data_Sales!$C$2:$C$1473,$B16) -> 1850.4 | G16: =SUMIFS(Data_Sales!$K$2:$K$1473,Data_Sales!$C$2:$C$1473,$B16) -> 925.2 | H16: =IF(F16=0,0,G16/F16) -> 0.5 | I16: =IF(F$21=0,0,F16/F$21) -> 0.054890095
... A20: =RANK(F20,$F$5:$F$20) -> 16 | B20: P12 | C20: Butter 200g | D20: Dairy | E20: =SUMIFS(Data_Sales!$F$2:$F$1473,Data_Sales!$C$2:$C$1473,$B20) -> 621 | F20: =SUMIFS(Data_Sales!$H$2:$H$1473,Data_Sales!$C$2:$C$1473,$B20) -> 1179.9 | G20: =SUMIFS(Data_Sales!$K$2:$K$1473,Data_Sales!$C$2:$C$1473,$B20) -> 372.6 | H20: =IF(F20=0,0,G20/F20) -> 0.31578947 | I20: =IF(F$21=0,0,F20/F$21) -> 0.035000445
A21: Total | E21: =SUM(E5:E20) -> 24892 | F21: =SUM(F5:F20) -> 33711 | G21: =SUM(G5:G20) -> 12908.25 | H21: =IF(F21=0,0,G21/F21) -> 0.38290914 | I21: =SUM(I5:I20) -> 1

Sheet Expense_Breakdown
A1: Expense Breakdown
A2: Categories are listed by total spend at the time the report was generated.
A4: Category | B4: 46204 | C4: 46235 | D4: 46266 | E4: Total | F4: % of Expenses
A5: Payroll | B5: =SUMIFS(Data_Expenses!$E$2:$E$40,Data_Expenses!$C$2:$C$40,$A5,Data_Expenses!$B$2:$B$40,B$4) -> 1400 | C5: =SUMIFS(Data_Expenses!$E$2:$E$40,Data_Expenses!$C$2:$C$40,$A5,Data_Expenses!$B$2:$B$40,C$4) -> 1400 | D5: =SUMIFS(Data_Expenses!$E$2:$E$40,Data_Expenses!$C$2:$C$40,$A5,Data_Expenses!$B$2:$B$40,D$4) -> 1400 | E5: =SUM(B5:D5) -> 4200 | F5: =IF(E$11=0,0,E5/E$11) -> 0.47151224
A6: Rent | B6: =SUMIFS(Data_Expenses!$E$2:$E$40,Data_Expenses!$C$2:$C$40,$A6,Data_Expenses!$B$2:$B$40,B$4) -> 900 | C6: =SUMIFS(Data_Expenses!$E$2:$E$40,Data_Expenses!$C$2:$C$40,$A6,Data_Expenses!$B$2:$B$40,C$4) -> 900 | D6: =SUMIFS(Data_Expenses!$E$2:$E$40,Data_Expenses!$C$2:$C$40,$A6,Data_Expenses!$B$2:$B$40,D$4) -> 900 | E6: =SUM(B6:D6) -> 2700 | F6: =IF(E$11=0,0,E6/E$11) -> 0.30311501
A7: Utilities | B7: =SUMIFS(Data_Expenses!$E$2:$E$40,Data_Expenses!$C$2:$C$40,$A7,Data_Expenses!$B$2:$B$40,B$4) -> 306.22 | C7: =SUMIFS(Data_Expenses!$E$2:$E$40,Data_Expenses!$C$2:$C$40,$A7,Data_Expenses!$B$2:$B$40,C$4) -> 280.83 | D7: =SUMIFS(Data_Expenses!$E$2:$E$40,Data_Expenses!$C$2:$C$40,$A7,Data_Expenses!$B$2:$B$40,D$4) -> 305.91 | E7: =SUM(B7:D7) -> 892.96 | F7: =IF(E$11=0,0,E7/E$11) -> 0.10024799
A8: Supplies | B8: =SUMIFS(Data_Expenses!$E$2:$E$40,Data_Expenses!$C$2:$C$40,$A8,Data_Expenses!$B$2:$B$40,B$4) -> 115.6 | C8: =SUMIFS(Data_Expenses!$E$2:$E$40,Data_Expenses!$C$2:$C$40,$A8,Data_Expenses!$B$2:$B$40,C$4) -> 237.41 | D8: =SUMIFS(Data_Expenses!$E$2:$E$40,Data_Expenses!$C$2:$C$40,$A8,Data_Expenses!$B$2:$B$40,D$4) -> 186.62 | E8: =SUM(B8:D8) -> 539.63 | F8: =IF(E$11=0,0,E8/E$11) -> 0.060581464
A9: Marketing | B9: =SUMIFS(Data_Expenses!$E$2:$E$40,Data_Expenses!$C$2:$C$40,$A9,Data_Expenses!$B$2:$B$40,B$4) -> 100.77 | C9: =SUMIFS(Data_Expenses!$E$2:$E$40,Data_Expenses!$C$2:$C$40,$A9,Data_Expenses!$B$2:$B$40,C$4) -> 97.89 | D9: =SUMIFS(Data_Expenses!$E$2:$E$40,Data_Expenses!$C$2:$C$40,$A9,Data_Expenses!$B$2:$B$40,D$4) -> 117.98 | E9: =SUM(B9:D9) -> 316.64 | F9: =IF(E$11=0,0,E9/E$11) -> 0.035547532
A10: Maintenance | B10: =SUMIFS(Data_Expenses!$E$2:$E$40,Data_Expenses!$C$2:$C$40,$A10,Data_Expenses!$B$2:$B$40,B$4) -> 34.35 | C10: =SUMIFS(Data_Expenses!$E$2:$E$40,Data_Expenses!$C$2:$C$40,$A10,Data_Expenses!$B$2:$B$40,C$4) -> 184.72 | D10: =SUMIFS(Data_Expenses!$E$2:$E$40,Data_Expenses!$C$2:$C$40,$A10,Data_Expenses!$B$2:$B$40,D$4) -> 39.21 | E10: =SUM(B10:D10) -> 258.28 | F10: =IF(E$11=0,0,E10/E$11) -> 0.028995758
A11: Total | B11: =SUM(B5:B10) -> 2856.94 | C11: =SUM(C5:C10) -> 3100.85 | D11: =SUM(D5:D10) -> 2949.72 | E11: =SUM(E5:E10) -> 8907.51 | F11: =SUM(F5:F10) -> 1

Sheet Inventory
A1: Product ID | B1: Product | C1: Category | D1: Unit Cost | E1: Unit Price | F1: Stock On Hand | G1: Reorder Level | H1: Status | I1: Stock Value | J1: Margin % | K1: Units Sold (period) | L1: Avg Daily Sales | M1: Days of Stock Left
A2: P01 | B2: Cola 600ml | C2: Beverages | D2: 0.6 | E2: 1 | F2: 40 | G2: 78 | H2: =IF(F2<=G2,"REORDER","OK") -> REORDER | I2: =F2*D2 -> 24 | J2: =IF(E2=0,0,(E2-D2)/E2) -> 0.4 | K2: =SUMIFS(Data_Sales!$F$2:$F$1473,Data_Sales!$C$2:$C$1473,A2) -> 2839 | L2: =K2/Summary!$B$5 -> 30.858696 | M2: =IF(L2=0,"",ROUND(F2/L2,1)) -> 1.3
A3: P02 | B3: Orange Soda 600ml | C3: Beverages | D3: 0.55 | E3: 0.95 | F3: 120 | G3: 54 | H3: =IF(F3<=G3,"REORDER","OK") -> OK | I3: =F3*D3 -> 66 | J3: =IF(E3=0,0,(E3-D3)/E3) -> 0.42105263 | K3: =SUMIFS(Data_Sales!$F$2:$F$1473,Data_Sales!$C$2:$C$1473,A3) -> 1988 | L3: =K3/Summary!$B$5 -> 21.608696 | M3: =IF(L3=0,"",ROUND(F3/L3,1)) -> 5.6
A4: P03 | B4: Bottled Water 1L | C4: Beverages | D4: 0.3 | E4: 0.6 | F4: 55 | G4: 90 | H4: =IF(F4<=G4,"REORDER","OK") -> REORDER | I4: =F4*D4 -> 16.5 | J4: =IF(E4=0,0,(E4-D4)/E4) -> 0.5 | K4: =SUMIFS(Data_Sales!$F$2:$F$1473,Data_Sales!$C$2:$C$1473,A4) -> 3084 | L4: =K4/Summary!$B$5 -> 33.521739 | M4: =IF(L4=0,"",ROUND(F4/L4,1)) -> 1.6
A5: P04 | B5: Fruit Juice 1L | C5: Beverages | D5: 0.9 | E5: 1.5 | F5: 70 | G5: 36 | H5: =IF(F5<=G5,"REORDER","OK") -> OK | I5: =F5*D5 -> 63 | J5: =IF(E5=0,0,(E5-D5)/E5) -> 0.4 | K5: =SUMIFS(Data_Sales!$F$2:$F$1473,Data_Sales!$C$2:$C$1473,A5) -> 1237 | L5: =K5/Summary!$B$5 -> 13.445652 | M5: =IF(L5=0,"",ROUND(F5/L5,1)) -> 5.2
A6: P05 | B6: Potato Chips | C6: Snacks | D6: 0.8 | E6: 1.3 | F6: 130 | G6: 60 | H6: =IF(F6<=G6,"REORDER","OK") -> OK | I6: =F6*D6 -> 104 | J6: =IF(E6=0,0,(E6-D6)/E6) -> 0.38461538 | K6: =SUMIFS(Data_Sales!$F$2:$F$1473,Data_Sales!$C$2:$C$1473,A6) -> 2161 | L6: =K6/Summary!$B$5 -> 23.48913 | M6: =IF(L6=0,"",ROUND(F6/L6,1)) -> 5.5
A7: P06 | B7: Salted Peanuts | C7: Snacks | D7: 0.5 | E7: 0.9 | F7: 90 | G7: 42 | H7: =IF(F7<=G7,"REORDER","OK") -> OK | I7: =F7*D7 -> 45 | J7: =IF(E7=0,0,(E7-D7)/E7) -> 0.44444444 | K7: =SUMIFS(Data_Sales!$F$2:$F$1473,Data_Sales!$C$2:$C$1473,A7) -> 1424 | L7: =K7/Summary!$B$5 -> 15.478261 | M7: =IF(L7=0,"",ROUND(F7/L7,1)) -> 5.8
A8: P07 | B8: Cookies | C8: Snacks | D8: 0.7 | E8: 1.2 | F8: 110 | G8: 48 | H8: =IF(F8<=G8,"REORDER","OK") -> OK | I8: =F8*D8 -> 77 | J8: =IF(E8=0,0,(E8-D8)/E8) -> 0.41666667 | K8: =SUMIFS(Data_Sales!$F$2:$F$1473,Data_Sales!$C$2:$C$1473,A8) -> 1795 | L8: =K8/Summary!$B$5 -> 19.51087 | M8: =IF(L8=0,"",ROUND(F8/L8,1)) -> 5.6
A9: P08 | B9: Chocolate Bar | C9: Snacks | D9: 0.45 | E9: 0.85 | F9: 150 | G9: 66 | H9: =IF(F9<=G9,"REORDER","OK") -> OK | I9: =F9*D9 -> 67.5 | J9: =IF(E9=0,0,(E9-D9)/E9) -> 0.47058824 | K9: =SUMIFS(Data_Sales!$F$2:$F$1473,Data_Sales!$C$2:$C$1473,A9) -> 2328 | L9: =K9/Summary!$B$5 -> 25.304348 | M9: =IF(L9=0,"",ROUND(F9/L9,1)) -> 5.9
A10: P09 | B10: Whole Milk 1L | C10: Dairy | D10: 0.85 | E10: 1.2 | F10: 35 | G10: 72 | H10: =IF(F10<=G10,"REORDER","OK") -> REORDER | I10: =F10*D10 -> 29.75 | J10: =IF(E10=0,0,(E10-D10)/E10) -> 0.29166667 | K10: =SUMIFS(Data_Sales!$F$2:$F$1473,Data_Sales!$C$2:$C$1473,A10) -> 2561 | L10: =K10/Summary!$B$5 -> 27.836957 | M10: =IF(L10=0,"",ROUND(F10/L10,1)) -> 1.3
A11: P10 | B11: Yogurt 1kg | C11: Dairy | D11: 1.4 | E11: 2.2 | F11: 45 | G11: 30 | H11: =IF(F11<=G11,"REORDER","OK") -> OK | I11: =F11*D11 -> 63 | J11: =IF(E11=0,0,(E11-D11)/E11) -> 0.36363636 | K11: =SUMIFS(Data_Sales!$F$2:$F$1473,Data_Sales!$C$2:$C$1473,A11) -> 1036 | L11: =K11/Summary!$B$5 -> 11.26087 | M11: =IF(L11=0,"",ROUND(F11/L11,1)) -> 4
A12: P11 | B12: Cheese 400g | C12: Dairy | D12: 2.6 | E12: 3.8 | F12: 30 | G12: 21 | H12: =IF(F12<=G12,"REORDER","OK") -> OK | I12: =F12*D12 -> 78 | J12: =IF(E12=0,0,(E12-D12)/E12) -> 0.31578947 | K12: =SUMIFS(Data_Sales!$F$2:$F$1473,Data_Sales!$C$2:$C$1473,A12) -> 738 | L12: =K12/Summary!$B$5 -> 8.0217391 | M12: =IF(L12=0,"",ROUND(F12/L12,1)) -> 3.7
A13: P12 | B13: Butter 200g | C13: Dairy | D13: 1.3 | E13: 1.9 | F13: 28 | G13: 18 | H13: =IF(F13<=G13,"REORDER","OK") -> OK | I13: =F13*D13 -> 36.4 | J13: =IF(E13=0,0,(E13-D13)/E13) -> 0.31578947 | K13: =SUMIFS(Data_Sales!$F$2:$F$1473,Data_Sales!$C$2:$C$1473,A13) -> 621 | L13: =K13/Summary!$B$5 -> 6.75 | M13: =IF(L13=0,"",ROUND(F13/L13,1)) -> 4.1
... A17: P16 | B17: Paper Towels | C17: Cleaning | D17: 1.6 | E17: 2.5 | F17: 36 | G17: 21 | H17: =IF(F17<=G17,"REORDER","OK") -> OK | I17: =F17*D17 -> 57.6 | J17: =IF(E17=0,0,(E17-D17)/E17) -> 0.36 | K17: =SUMIFS(Data_Sales!$F$2:$F$1473,Data_Sales!$C$2:$C$1473,A17) -> 752 | L17: =K17/Summary!$B$5 -> 8.173913 | M17: =IF(L17=0,"",ROUND(F17/L17,1)) -> 4.4
A18: Total | I18: =SUM(I2:I17) -> 875.15

Sheet Data_Sales
A1: Date | B1: Month | C1: Product ID | D1: Product | E1: Category | F1: Units | G1: Unit Price | H1: Revenue | I1: Unit Cost | J1: COGS | K1: Gross Profit
A2: 46204 | B2: =DATE(YEAR(A2),MONTH(A2),1) -> 46204 | C2: P01 | D2: Cola 600ml | E2: Beverages | F2: 25 | G2: 1 | H2: =F2*G2 -> 25 | I2: =INDEX(Inventory!$D$2:$D$17,MATCH(C2,Inventory!$A$2:$A$17,0)) -> 0.6 | J2: =F2*I2 -> 15 | K2: =H2-J2 -> 10
A3: 46204 | B3: =DATE(YEAR(A3),MONTH(A3),1) -> 46204 | C3: P02 | D3: Orange Soda 600ml | E3: Beverages | F3: 17 | G3: 0.95 | H3: =F3*G3 -> 16.15 | I3: =INDEX(Inventory!$D$2:$D$17,MATCH(C3,Inventory!$A$2:$A$17,0)) -> 0.55 | J3: =F3*I3 -> 9.35 | K3: =H3-J3 -> 6.8
A4: 46204 | B4: =DATE(YEAR(A4),MONTH(A4),1) -> 46204 | C4: P03 | D4: Bottled Water 1L | E4: Beverages | F4: 29 | G4: 0.6 | H4: =F4*G4 -> 17.4 | I4: =INDEX(Inventory!$D$2:$D$17,MATCH(C4,Inventory!$A$2:$A$17,0)) -> 0.3 | J4: =F4*I4 -> 8.7 | K4: =H4-J4 -> 8.7
A5: 46204 | B5: =DATE(YEAR(A5),MONTH(A5),1) -> 46204 | C5: P04 | D5: Fruit Juice 1L | E5: Beverages | F5: 14 | G5: 1.5 | H5: =F5*G5 -> 21 | I5: =INDEX(Inventory!$D$2:$D$17,MATCH(C5,Inventory!$A$2:$A$17,0)) -> 0.9 | J5: =F5*I5 -> 12.6 | K5: =H5-J5 -> 8.4
A6: 46204 | B6: =DATE(YEAR(A6),MONTH(A6),1) -> 46204 | C6: P05 | D6: Potato Chips | E6: Snacks | F6: 19 | G6: 1.3 | H6: =F6*G6 -> 24.7 | I6: =INDEX(Inventory!$D$2:$D$17,MATCH(C6,Inventory!$A$2:$A$17,0)) -> 0.8 | J6: =F6*I6 -> 15.2 | K6: =H6-J6 -> 9.5
A7: 46204 | B7: =DATE(YEAR(A7),MONTH(A7),1) -> 46204 | C7: P06 | D7: Salted Peanuts | E7: Snacks | F7: 9 | G7: 0.9 | H7: =F7*G7 -> 8.1 | I7: =INDEX(Inventory!$D$2:$D$17,MATCH(C7,Inventory!$A$2:$A$17,0)) -> 0.5 | J7: =F7*I7 -> 4.5 | K7: =H7-J7 -> 3.6
A8: 46204 | B8: =DATE(YEAR(A8),MONTH(A8),1) -> 46204 | C8: P07 | D8: Cookies | E8: Snacks | F8: 17 | G8: 1.2 | H8: =F8*G8 -> 20.4 | I8: =INDEX(Inventory!$D$2:$D$17,MATCH(C8,Inventory!$A$2:$A$17,0)) -> 0.7 | J8: =F8*I8 -> 11.9 | K8: =H8-J8 -> 8.5
A9: 46204 | B9: =DATE(YEAR(A9),MONTH(A9),1) -> 46204 | C9: P08 | D9: Chocolate Bar | E9: Snacks | F9: 21 | G9: 0.85 | H9: =F9*G9 -> 17.85 | I9: =INDEX(Inventory!$D$2:$D$17,MATCH(C9,Inventory!$A$2:$A$17,0)) -> 0.45 | J9: =F9*I9 -> 9.45 | K9: =H9-J9 -> 8.4
A10: 46204 | B10: =DATE(YEAR(A10),MONTH(A10),1) -> 46204 | C10: P09 | D10: Whole Milk 1L | E10: Dairy | F10: 23 | G10: 1.2 | H10: =F10*G10 -> 27.6 | I10: =INDEX(Inventory!$D$2:$D$17,MATCH(C10,Inventory!$A$2:$A$17,0)) -> 0.85 | J10: =F10*I10 -> 19.55 | K10: =H10-J10 -> 8.05
A11: 46204 | B11: =DATE(YEAR(A11),MONTH(A11),1) -> 46204 | C11: P10 | D11: Yogurt 1kg | E11: Dairy | F11: 10 | G11: 2.2 | H11: =F11*G11 -> 22 | I11: =INDEX(Inventory!$D$2:$D$17,MATCH(C11,Inventory!$A$2:$A$17,0)) -> 1.4 | J11: =F11*I11 -> 14 | K11: =H11-J11 -> 8
A12: 46204 | B12: =DATE(YEAR(A12),MONTH(A12),1) -> 46204 | C12: P11 | D12: Cheese 400g | E12: Dairy | F12: 7 | G12: 3.8 | H12: =F12*G12 -> 26.6 | I12: =INDEX(Inventory!$D$2:$D$17,MATCH(C12,Inventory!$A$2:$A$17,0)) -> 2.6 | J12: =F12*I12 -> 18.2 | K12: =H12-J12 -> 8.4
A13: 46204 | B13: =DATE(YEAR(A13),MONTH(A13),1) -> 46204 | C13: P12 | D13: Butter 200g | E13: Dairy | F13: 8 | G13: 1.9 | H13: =F13*G13 -> 15.2 | I13: =INDEX(Inventory!$D$2:$D$17,MATCH(C13,Inventory!$A$2:$A$17,0)) -> 1.3 | J13: =F13*I13 -> 10.4 | K13: =H13-J13 -> 4.8
... A1473: 46295 | B1473: =DATE(YEAR(A1473),MONTH(A1473),1) -> 46266 | C1473: P16 | D1473: Paper Towels | E1473: Cleaning | F1473: 7 | G1473: 2.5 | H1473: =F1473*G1473 -> 17.5 | I1473: =INDEX(Inventory!$D$2:$D$17,MATCH(C1473,Inventory!$A$2:$A$17,0)) -> 1.6 | J1473: =F1473*I1473 -> 11.2 | K1473: =H1473-J1473 -> 6.3

Sheet Data_Expenses
A1: Date | B1: Month | C1: Category | D1: Description | E1: Amount
A2: 46204 | B2: =DATE(YEAR(A2),MONTH(A2),1) -> 46204 | C2: Rent | D2: Store rent | E2: 900
A3: 46208 | B3: =DATE(YEAR(A3),MONTH(A3),1) -> 46204 | C3: Utilities | D3: Electricity | E3: 207.36
A4: 46211 | B4: =DATE(YEAR(A4),MONTH(A4),1) -> 46204 | C4: Utilities | D4: Water | E4: 53.86
A5: 46213 | B5: =DATE(YEAR(A5),MONTH(A5),1) -> 46204 | C5: Utilities | D5: Internet | E5: 45
A6: 46214 | B6: =DATE(YEAR(A6),MONTH(A6),1) -> 46204 | C6: Supplies | D6: Shopping bags | E6: 19.4
A7: 46215 | B7: =DATE(YEAR(A7),MONTH(A7),1) -> 46204 | C7: Marketing | D7: Flyers and social media ads | E7: 100.77
A8: 46218 | B8: =DATE(YEAR(A8),MONTH(A8),1) -> 46204 | C8: Payroll | D8: Payroll (first half) | E8: 700
A9: 46223 | B9: =DATE(YEAR(A9),MONTH(A9),1) -> 46204 | C9: Supplies | D9: Receipt paper | E9: 45
A10: 46225 | B10: =DATE(YEAR(A10),MONTH(A10),1) -> 46204 | C10: Maintenance | D10: Minor repairs | E10: 34.35
A11: 46225 | B11: =DATE(YEAR(A11),MONTH(A11),1) -> 46204 | C11: Supplies | D11: Cleaning supplies | E11: 31.86
A12: 46227 | B12: =DATE(YEAR(A12),MONTH(A12),1) -> 46204 | C12: Supplies | D12: Price labels | E12: 19.34
A13: 46231 | B13: =DATE(YEAR(A13),MONTH(A13),1) -> 46204 | C13: Payroll | D13: Payroll (second half) | E13: 700
... A40: 46293 | B40: =DATE(YEAR(A40),MONTH(A40),1) -> 46266 | C40: Payroll | D40: Payroll (second half) | E40: 700
